nonebot_plugin_trace_moe/__init__.py
nonebot_plugin_trace_moe-0.1.0.dist-info/LICENSE
nonebot_plugin_trace_moe-0.1.0.dist-info/WHEEL
nonebot_plugin_trace_moe-0.1.0.dist-info/METADATA
nonebot_plugin_trace_moe-0.1.0.dist-info/RECORD
