Metadata-Version: 2.1
Name: nonebot-plugin-trace-moe
Version: 0.1.0
Summary: 适用于nonebot2 v11的基于trace.moe的动画截图场景追溯插件
Home-page: https://github.com/Ikaros-521/nonebot_plugin_trace_moe
License: MIT
Author: Ikaros
Author-email: 327209194@qq.com
Requires-Python: >=3.8,<4.0
Classifier: License :: OSI Approved :: MIT License
Classifier: Programming Language :: Python :: 3
Classifier: Programming Language :: Python :: 3.8
Classifier: Programming Language :: Python :: 3.9
Classifier: Programming Language :: Python :: 3.10
Classifier: Programming Language :: Python :: 3.11
Requires-Dist: aiohttp (>=3.8.3,<4.0.0)
Requires-Dist: nonebot-adapter-onebot (>=2.1.3,<3.0.0)
Requires-Dist: nonebot2 (>=2.0.0b5,<3.0.0)
Project-URL: Documentation, https://github.com/Ikaros-521/nonebot_plugin_trace_moe/blob/master/README.md
Project-URL: Repository, https://github.com/Ikaros-521/nonebot_plugin_trace_moe
